pflops/__init__.py
pflops/common.py
pflops/dataset.py
pflops/fs.py
pflops/image.py
pflops/job.py
pflops/main.py
pflops-0.1.5.dist-info/entry_points.txt
pflops-0.1.5.dist-info/WHEEL
pflops-0.1.5.dist-info/METADATA
pflops-0.1.5.dist-info/RECORD
